LICENSE
MANIFEST
MANIFEST.in
README.rst
__init__.py
__init__.py2
__init__.py3
datetime_handler.py
datetime_handler.py2
datetime_handler.py3
setup.cfg
setup.py
Cerealizer.egg-info/PKG-INFO
Cerealizer.egg-info/SOURCES.txt
Cerealizer.egg-info/dependency_links.txt
Cerealizer.egg-info/top_level.txt
test/regtest.py
test/test1.py