Metadata-Version: 2.1
Name: Cerealizer
Version: 0.8.4
Summary: A secure pickle-like module
Home-page: http://www.lesfleursdunormal.fr/static/informatique/cerealizer/index_en.html
Author: Lamy Jean-Baptiste (Jiba)
Author-email: jibalamy@free.fr
License: Python licence
Classifier: Development Status :: 5 - Production/Stable
Classifier: Intended Audience :: Developers
Classifier: License :: OSI Approved :: Python Software Foundation License
Classifier: Programming Language :: Python :: 2
Classifier: Programming Language :: Python :: 3
Classifier: Topic :: Security
Classifier: Topic :: Software Development :: Libraries :: Python Modules
License-File: LICENSE
